go1pylib/__init__.py
go1pylib/go1.py
go1pylib/mqtt/__init__.py
go1pylib/mqtt/client.py
go1pylib/mqtt/handler.py
go1pylib/mqtt/state.py
go1pylib/mqtt/topics.py
go1pylib/mqtt/receivers/__init__.py
go1pylib/mqtt/receivers/bms.py
go1pylib/mqtt/receivers/robot.py
go1pylib-0.1.5.dist-info/LICENSE
go1pylib-0.1.5.dist-info/METADATA
go1pylib-0.1.5.dist-info/WHEEL
go1pylib-0.1.5.dist-info/entry_points.txt
go1pylib-0.1.5.dist-info/top_level.txt
go1pylib-0.1.5.dist-info/RECORD
